dieboldmariano/__init__.py
dieboldmariano/dieboldmariano.py
dieboldmariano/dieboldmariano.pyi
dieboldmariano-1.1.0.dist-info/LICENSE
dieboldmariano-1.1.0.dist-info/METADATA
dieboldmariano-1.1.0.dist-info/WHEEL
dieboldmariano-1.1.0.dist-info/top_level.txt
dieboldmariano-1.1.0.dist-info/RECORD
