Metadata-Version: 2.2
Name: dieboldmariano
Version: 1.1.0
Summary: Diebold-Mariano test
Home-page: https://github.com/edoannunziata/dieboldmariano
Author: Edoardo Annunziata
Author-email: annunziata.edoardo@outlook.com
Classifier: Programming Language :: Python :: 3
Classifier: License :: OSI Approved :: MIT License
Classifier: Operating System :: OS Independent
Requires-Python: >=3.6
License-File: LICENSE
